odoo8_addon_crm_claim_product_supplier-8.0.1.0.0.99.dev20-py2.7-nspkg.pth
odoo8_addon_crm_claim_product_supplier-8.0.1.0.0.99.dev20.dist-info/METADATA
odoo8_addon_crm_claim_product_supplier-8.0.1.0.0.99.dev20.dist-info/RECORD
odoo8_addon_crm_claim_product_supplier-8.0.1.0.0.99.dev20.dist-info/WHEEL
odoo8_addon_crm_claim_product_supplier-8.0.1.0.0.99.dev20.dist-info/namespace_packages.txt
odoo8_addon_crm_claim_product_supplier-8.0.1.0.0.99.dev20.dist-info/top_level.txt
odoo_addons/crm_claim_product_supplier/README.rst
odoo_addons/crm_claim_product_supplier/__init__.py
odoo_addons/crm_claim_product_supplier/__openerp__.py
odoo_addons/crm_claim_product_supplier/i18n/bg.po
odoo_addons/crm_claim_product_supplier/i18n/ca.po
odoo_addons/crm_claim_product_supplier/i18n/de.po
odoo_addons/crm_claim_product_supplier/i18n/el_GR.po
odoo_addons/crm_claim_product_supplier/i18n/es.po
odoo_addons/crm_claim_product_supplier/i18n/es_VE.po
odoo_addons/crm_claim_product_supplier/i18n/fi.po
odoo_addons/crm_claim_product_supplier/i18n/fr.po
odoo_addons/crm_claim_product_supplier/i18n/fr_FR.po
odoo_addons/crm_claim_product_supplier/i18n/it.po
odoo_addons/crm_claim_product_supplier/i18n/nl_NL.po
odoo_addons/crm_claim_product_supplier/i18n/pt_BR.po
odoo_addons/crm_claim_product_supplier/i18n/pt_PT.po
odoo_addons/crm_claim_product_supplier/i18n/sk.po
odoo_addons/crm_claim_product_supplier/i18n/sl.po
odoo_addons/crm_claim_product_supplier/models/__init__.py
odoo_addons/crm_claim_product_supplier/models/claim_line.py
odoo_addons/crm_claim_product_supplier/static/description/icon.png
odoo_addons/crm_claim_product_supplier/tests/__init__.py
odoo_addons/crm_claim_product_supplier/tests/test_crm_claim_product_supplier.py
